gelato/__init__.py
gelato/expr.py
gelato/glt.py
gelato/utils.py
gelato/version.py
gelato/printing/__init__.py
gelato/printing/latex.py
gelato/tests/__init__.py
gelato/tests/test_bilinear_2d.py
gelato/tests/test_bilinear_3d.py
gelato/tests/test_gelatize_1d.py
gelato/tests/test_gelatize_2d.py
gelato/tests/test_gelatize_3d.py
gelato/tests/test_glt_expr_2d.py
gelato/tests/test_glt_symbol.py
gelato-0.12.0.dist-info/LICENSE
gelato-0.12.0.dist-info/METADATA
gelato-0.12.0.dist-info/WHEEL
gelato-0.12.0.dist-info/top_level.txt
gelato-0.12.0.dist-info/zip-safe
gelato-0.12.0.dist-info/RECORD
