Metadata-Version: 2.1
Name: gelato
Version: 0.12.0
Summary: A Python library for Generalized Locally Toeplitz theory for Isogeometric Analysis.
Home-page: https://github.com/ratnania/GeLaTo
Author: Ahmed Ratnani
Author-email: ahmed.ratnani@ipp.mpg.de
License: LICENSE
Keywords: math
License-File: LICENSE
Requires-Dist: sympy (>=1.2)
Requires-Dist: numpy (>=1.13)
Requires-Dist: scipy (>=0.18)
Requires-Dist: matplotlib
Requires-Dist: sympde (>=0.10)
